git_flux/__init__.py
git_flux/__main__.py
git_flux/commands/__init__.py
git_flux/commands/log.py
git_flux/repo.py
git_flux-0.1.0.dist-info/entry_points.txt
git_flux-0.1.0.dist-info/LICENSE
git_flux-0.1.0.dist-info/METADATA
git_flux-0.1.0.dist-info/WHEEL
git_flux-0.1.0.dist-info/RECORD
